bruno_memory/__init__.py
bruno_memory/__version__.py
bruno_memory/exceptions.py
bruno_memory/factory.py
bruno_memory/backends/__init__.py
bruno_memory/backends/postgresql/__init__.py
bruno_memory/backends/postgresql/backend.py
bruno_memory/backends/postgresql/schema.py
bruno_memory/backends/redis/__init__.py
bruno_memory/backends/redis/backend.py
bruno_memory/backends/sqlite/__init__.py
bruno_memory/backends/sqlite/backend.py
bruno_memory/backends/sqlite/schema.py
bruno_memory/backends/vector/__init__.py
bruno_memory/backends/vector/chromadb_backend.py
bruno_memory/backends/vector/qdrant_backend.py
bruno_memory/base/__init__.py
bruno_memory/base/base_backend.py
bruno_memory/base/config.py
bruno_memory/managers/__init__.py
bruno_memory/managers/compressor.py
bruno_memory/managers/context_builder.py
bruno_memory/managers/conversation.py
bruno_memory/managers/embedding.py
bruno_memory/managers/retriever.py
bruno_memory/utils/__init__.py
bruno_memory/utils/analytics.py
bruno_memory/utils/backup.py
bruno_memory/utils/cache.py
bruno_memory/utils/performance.py
bruno_memory/utils/prioritization.py
bruno_memory/utils/security.py
bruno_memory-0.1.5.dist-info/METADATA
bruno_memory-0.1.5.dist-info/WHEEL
bruno_memory-0.1.5.dist-info/entry_points.txt
bruno_memory-0.1.5.dist-info/licenses/LICENSE
bruno_memory-0.1.5.dist-info/RECORD
