Metadata-Version: 2.4
Name: bruno-memory
Version: 0.1.5
Summary: Memory storage and retrieval system for Bruno AI Platform
Project-URL: Homepage, https://github.com/meggy-ai/bruno-memory
Project-URL: Documentation, https://github.com/meggy-ai/bruno-memory#readme
Project-URL: Repository, https://github.com/meggy-ai/bruno-memory.git
Project-URL: Issues, https://github.com/meggy-ai/bruno-memory/issues
Author-email: meggy-ai <contact@meggy-ai.com>
License-Expression: MIT
License-File: LICENSE
Keywords: ai,assistant,bruno-ai,chat,conversation,embeddings,memory,storage,vector-database
Classifier: Development Status :: 4 - Beta
Classifier: Intended Audience :: Developers
Classifier: License :: OSI Approved :: MIT License
Classifier: Operating System :: OS Independent
Classifier: Programming Language :: Python :: 3
Classifier: Programming Language :: Python :: 3.10
Classifier: Programming Language :: Python :: 3.11
Classifier: Programming Language :: Python :: 3.12
Classifier: Topic :: Scientific/Engineering :: Artificial Intelligence
Classifier: Topic :: Software Development :: Libraries :: Python Modules
Requires-Python: >=3.10
Requires-Dist: bruno-core>=0.1.0
Requires-Dist: bruno-llm>=0.1.0
Requires-Dist: pydantic>=2.5.0
Requires-Dist: python-dateutil>=2.8.2
Requires-Dist: typing-extensions>=4.8.0
Provides-Extra: advanced
Requires-Dist: cryptography>=41.0.0; extra == 'advanced'
Requires-Dist: numpy>=1.24.0; extra == 'advanced'
Provides-Extra: all
Requires-Dist: aiosqlite>=0.19.0; extra == 'all'
Requires-Dist: asyncpg>=0.29.0; extra == 'all'
Requires-Dist: chromadb>=0.4.18; extra == 'all'
Requires-Dist: cryptography>=41.0.0; extra == 'all'
Requires-Dist: numpy>=1.24.0; extra == 'all'
Requires-Dist: psycopg2-binary>=2.9.9; extra == 'all'
Requires-Dist: qdrant-client>=1.7.0; extra == 'all'
Requires-Dist: redis[hiredis]>=5.0.0; extra == 'all'
Requires-Dist: sentence-transformers>=2.2.2; extra == 'all'
Requires-Dist: torch>=2.1.0; extra == 'all'
Provides-Extra: dev
Requires-Dist: bandit>=1.7.5; extra == 'dev'
Requires-Dist: black>=23.12.0; extra == 'dev'
Requires-Dist: mypy>=1.7.1; extra == 'dev'
Requires-Dist: pip-audit>=2.6.1; extra == 'dev'
Requires-Dist: pre-commit>=3.6.0; extra == 'dev'
Requires-Dist: pytest-asyncio>=0.21.1; extra == 'dev'
Requires-Dist: pytest-cov>=4.1.0; extra == 'dev'
Requires-Dist: pytest-mock>=3.12.0; extra == 'dev'
Requires-Dist: pytest>=7.4.3; extra == 'dev'
Requires-Dist: ruff>=0.1.8; extra == 'dev'
Provides-Extra: docs
Requires-Dist: mkdocs-autorefs>=0.5.0; extra == 'docs'
Requires-Dist: mkdocs-material>=9.4.0; extra == 'docs'
Requires-Dist: mkdocs>=1.5.3; extra == 'docs'
Requires-Dist: mkdocstrings[python]>=0.24.0; extra == 'docs'
Provides-Extra: embeddings
Requires-Dist: sentence-transformers>=2.2.2; extra == 'embeddings'
Requires-Dist: torch>=2.1.0; extra == 'embeddings'
Provides-Extra: postgresql
Requires-Dist: asyncpg>=0.29.0; extra == 'postgresql'
Requires-Dist: psycopg2-binary>=2.9.9; extra == 'postgresql'
Provides-Extra: redis
Requires-Dist: redis[hiredis]>=5.0.0; extra == 'redis'
Provides-Extra: sqlite
Requires-Dist: aiosqlite>=0.19.0; extra == 'sqlite'
Provides-Extra: test
Requires-Dist: pytest-asyncio>=0.21.1; extra == 'test'
Requires-Dist: pytest-cov>=4.1.0; extra == 'test'
Requires-Dist: pytest-mock>=3.12.0; extra == 'test'
Requires-Dist: pytest-timeout>=2.2.0; extra == 'test'
Requires-Dist: pytest>=7.4.3; extra == 'test'
Provides-Extra: test-services
Requires-Dist: docker>=6.1.0; extra == 'test-services'
Requires-Dist: testcontainers>=3.7.0; extra == 'test-services'
Provides-Extra: vector
Requires-Dist: chromadb>=0.4.18; extra == 'vector'
Requires-Dist: qdrant-client>=1.7.0; extra == 'vector'
